cambiato/__init__.py
cambiato/__main__.py
cambiato/core.py
cambiato/exceptions.py
cambiato/log.py
cambiato/metadata.py
cambiato/py.typed
cambiato/app/__init__.py
cambiato/app/auth.py
cambiato/app/config.py
cambiato/app/main.py
cambiato/app/session_state.py
cambiato/app/setup.py
cambiato/app/_pages/__init__.py
cambiato/app/_pages/home.py
cambiato/app/_pages/init.py
cambiato/app/_pages/order.py
cambiato/app/_pages/sign_in.py
cambiato/app/components/__init__.py
cambiato/app/components/buttons.py
cambiato/app/components/core.py
cambiato/app/components/icons.py
cambiato/app/components/keys.py
cambiato/app/components/selectors.py
cambiato/app/components/sidebar.py
cambiato/app/components/dataframes/__init__.py
cambiato/app/components/dataframes/core.py
cambiato/app/components/dataframes/edit_orders.py
cambiato/app/components/forms/__init__.py
cambiato/app/components/forms/create_order_form.py
cambiato/app/controllers/__init__.py
cambiato/app/controllers/init.py
cambiato/app/controllers/order.py
cambiato/app/controllers/sign_in.py
cambiato/app/database/__init__.py
cambiato/app/database/cache.py
cambiato/app/views/__init__.py
cambiato/app/views/init.py
cambiato/app/views/orders/__init__.py
cambiato/app/views/orders/edit_orders_view.py
cambiato/cli/__init__.py
cambiato/cli/main.py
cambiato/cli/commands/__init__.py
cambiato/cli/commands/run.py
cambiato/config/__init__.py
cambiato/config/config.py
cambiato/config/core.py
cambiato/config/log.py
cambiato/database/__init__.py
cambiato/database/core.py
cambiato/database/init.py
cambiato/database/crud/__init__.py
cambiato/database/crud/checklist.py
cambiato/database/crud/core.py
cambiato/database/crud/customer.py
cambiato/database/crud/facility.py
cambiato/database/crud/order.py
cambiato/database/crud/user.py
cambiato/database/crud/utility.py
cambiato/database/models/__init__.py
cambiato/database/models/core.py
cambiato/database/models/default.py
cambiato/database/models/relations.py
cambiato/models/__init__.py
cambiato-0.4.1.dist-info/licenses/LICENSE
cambiato-0.4.1.dist-info/METADATA
cambiato-0.4.1.dist-info/WHEEL
cambiato-0.4.1.dist-info/entry_points.txt
cambiato-0.4.1.dist-info/top_level.txt
cambiato-0.4.1.dist-info/RECORD
