Metadata-Version: 2.4
Name: Cambiato
Version: 0.4.1
Summary: The simple yet powerful system for changing utility devices.
Author-email: Anton Lydell <anton.lydell@tuta.com>
License: GNU General Public License v3 (GPLv3)
Project-URL: Bug Tracker, https://github.com/antonlydell/Cambiato/issues
Project-URL: Documentation, https://github.com/antonlydell/Cambiato
Project-URL: Source Code, https://github.com/antonlydell/Cambiato
Keywords: Change,Device,Device Change,District Cooling,District Heating,Electricity,Meter,Meter Change,Utility,Streamlit,Water,Web
Classifier: Development Status :: 1 - Planning
Classifier: Environment :: Web Environment
Classifier: Intended Audience :: End Users/Desktop
Classifier: Intended Audience :: Other Audience
Classifier: Natural Language :: English
Classifier: Natural Language :: Swedish
Classifier: Operating System :: OS Independent
Classifier: Programming Language :: Python :: 3 :: Only
Classifier: Programming Language :: Python :: 3.11
Classifier: Programming Language :: Python :: 3.12
Classifier: Programming Language :: Python :: 3.13
Classifier: Topic :: Office/Business
Classifier: Topic :: Scientific/Engineering
Requires-Python: >=3.11
License-File: LICENSE
Requires-Dist: click>=8.0
Requires-Dist: pydantic>=2.0
Requires-Dist: streamlit>=1.40
Requires-Dist: streamlit-passwordless>=0.16
Requires-Dist: sqlalchemy>=2.0
Dynamic: license-file
